scrapli/__init__.py
scrapli/decorators.py
scrapli/exceptions.py
scrapli/factory.py
scrapli/helper.py
scrapli/logging.py
scrapli/py.typed
scrapli/response.py
scrapli/settings.py
scrapli/ssh_config.py
scrapli/channel/__init__.py
scrapli/channel/async_channel.py
scrapli/channel/base_channel.py
scrapli/channel/sync_channel.py
scrapli/driver/__init__.py
scrapli/driver/base/__init__.py
scrapli/driver/base/async_driver.py
scrapli/driver/base/base_driver.py
scrapli/driver/base/sync_driver.py
scrapli/driver/core/__init__.py
scrapli/driver/core/arista_eos/__init__.py
scrapli/driver/core/arista_eos/async_driver.py
scrapli/driver/core/arista_eos/base_driver.py
scrapli/driver/core/arista_eos/sync_driver.py
scrapli/driver/core/cisco_iosxe/__init__.py
scrapli/driver/core/cisco_iosxe/async_driver.py
scrapli/driver/core/cisco_iosxe/base_driver.py
scrapli/driver/core/cisco_iosxe/sync_driver.py
scrapli/driver/core/cisco_iosxr/__init__.py
scrapli/driver/core/cisco_iosxr/async_driver.py
scrapli/driver/core/cisco_iosxr/base_driver.py
scrapli/driver/core/cisco_iosxr/sync_driver.py
scrapli/driver/core/cisco_nxos/__init__.py
scrapli/driver/core/cisco_nxos/async_driver.py
scrapli/driver/core/cisco_nxos/base_driver.py
scrapli/driver/core/cisco_nxos/sync_driver.py
scrapli/driver/core/juniper_junos/__init__.py
scrapli/driver/core/juniper_junos/async_driver.py
scrapli/driver/core/juniper_junos/base_driver.py
scrapli/driver/core/juniper_junos/sync_driver.py
scrapli/driver/generic/__init__.py
scrapli/driver/generic/async_driver.py
scrapli/driver/generic/base_driver.py
scrapli/driver/generic/sync_driver.py
scrapli/driver/network/__init__.py
scrapli/driver/network/async_driver.py
scrapli/driver/network/base_driver.py
scrapli/driver/network/sync_driver.py
scrapli/transport/__init__.py
scrapli/transport/base/__init__.py
scrapli/transport/base/async_transport.py
scrapli/transport/base/base_socket.py
scrapli/transport/base/base_transport.py
scrapli/transport/base/sync_transport.py
scrapli-2024.7.30.dist-info/LICENSE
scrapli-2024.7.30.dist-info/METADATA
scrapli-2024.7.30.dist-info/WHEEL
scrapli-2024.7.30.dist-info/top_level.txt
scrapli-2024.7.30.dist-info/RECORD
